pkrd/__init__.py
pkrd-0.0.1.dist-info/licenses/LICENSE
pkrd-0.0.1.dist-info/METADATA
pkrd-0.0.1.dist-info/WHEEL
pkrd-0.0.1.dist-info/top_level.txt
pkrd-0.0.1.dist-info/RECORD
