Metadata-Version: 2.4
Name: pkrd
Version: 0.0.1
Summary: PKRD.AI Official Lib
Author-email: "PKRD, LLC" <contact@pkrd.ai>
License: MIT
Requires-Python: >=3.7
License-File: LICENSE
Dynamic: license-file
